PythonWuJianduXuexiShiyongZhinanChuyi/README.md
PythonWuJianduXuexiShiyongZhinanChuyi/__init__.py
PythonWuJianduXuexiShiyongZhinanChuyi/__main__.py
PythonWuJianduXuexiShiyongZhinanChuyi/file.epub
PythonWuJianduXuexiShiyongZhinanChuyi/index.html
PythonWuJianduXuexiShiyongZhinanChuyi/css/__init__.py
PythonWuJianduXuexiShiyongZhinanChuyi/css/annotations.css
PythonWuJianduXuexiShiyongZhinanChuyi/css/main.css
PythonWuJianduXuexiShiyongZhinanChuyi/css/normalize.css
PythonWuJianduXuexiShiyongZhinanChuyi/css/popup.css
PythonWuJianduXuexiShiyongZhinanChuyi/font/__init__.py
PythonWuJianduXuexiShiyongZhinanChuyi/font/fontello.eot
PythonWuJianduXuexiShiyongZhinanChuyi/font/fontello.svg
PythonWuJianduXuexiShiyongZhinanChuyi/font/fontello.ttf
PythonWuJianduXuexiShiyongZhinanChuyi/font/fontello.woff
PythonWuJianduXuexiShiyongZhinanChuyi/img/__init__.py
PythonWuJianduXuexiShiyongZhinanChuyi/img/annotator-glyph-sprite.png
PythonWuJianduXuexiShiyongZhinanChuyi/img/annotator-icon-sprite.png
PythonWuJianduXuexiShiyongZhinanChuyi/img/apple-touch-icon.png
PythonWuJianduXuexiShiyongZhinanChuyi/img/cancelfullscreen.png
PythonWuJianduXuexiShiyongZhinanChuyi/img/close.png
PythonWuJianduXuexiShiyongZhinanChuyi/img/fullscreen.png
PythonWuJianduXuexiShiyongZhinanChuyi/img/loader.gif
PythonWuJianduXuexiShiyongZhinanChuyi/img/menu-icon.png
PythonWuJianduXuexiShiyongZhinanChuyi/img/save.png
PythonWuJianduXuexiShiyongZhinanChuyi/img/saved.png
PythonWuJianduXuexiShiyongZhinanChuyi/img/settings-s.png
PythonWuJianduXuexiShiyongZhinanChuyi/img/settings.png
PythonWuJianduXuexiShiyongZhinanChuyi/img/star.png
PythonWuJianduXuexiShiyongZhinanChuyi/js/__init__.py
PythonWuJianduXuexiShiyongZhinanChuyi/js/epub.js
PythonWuJianduXuexiShiyongZhinanChuyi/js/epub.min.js
PythonWuJianduXuexiShiyongZhinanChuyi/js/epub.min.map
PythonWuJianduXuexiShiyongZhinanChuyi/js/hooks.min.js
PythonWuJianduXuexiShiyongZhinanChuyi/js/hooks.min.map
PythonWuJianduXuexiShiyongZhinanChuyi/js/reader.js
python_wu_jiandu_xuexi_shiyong_zhinan_chuyi-2024.3.5.0.dist-info/METADATA
python_wu_jiandu_xuexi_shiyong_zhinan_chuyi-2024.3.5.0.dist-info/WHEEL
python_wu_jiandu_xuexi_shiyong_zhinan_chuyi-2024.3.5.0.dist-info/entry_points.txt
python_wu_jiandu_xuexi_shiyong_zhinan_chuyi-2024.3.5.0.dist-info/top_level.txt
python_wu_jiandu_xuexi_shiyong_zhinan_chuyi-2024.3.5.0.dist-info/RECORD
